completely/__init__.py
completely-0.1.0.dist-info/LICENSE
completely-0.1.0.dist-info/METADATA
completely-0.1.0.dist-info/WHEEL
completely-0.1.0.dist-info/top_level.txt
completely-0.1.0.dist-info/RECORD
