Metadata-Version: 2.1
Name: completely
Version: 0.1.0
Summary: A simple tool to measure data completeness
Home-page: https://github.com/INNOVINATI/completely
Author: Maximilian Wolf
Author-email: maximilian.wolf@innovinati.com
License: UNKNOWN
Project-URL: Bug Reports, https://github.com/INNOVINATI/completely/issues
Project-URL: Source, https://github.com/INNOVINATI/completely/
Platform: UNKNOWN
Classifier: Development Status :: 5 - Production/Stable
Classifier: Intended Audience :: Developers
Classifier: License :: OSI Approved :: MIT License
Classifier: Programming Language :: Python :: 3
Classifier: Programming Language :: Python :: 3.7
Classifier: Programming Language :: Python :: 3.8
Classifier: Programming Language :: Python :: 3.9
Classifier: Programming Language :: Python :: 3 :: Only
Requires-Python: >=3.6, <4
